{
  "_": "Message",
  "id": 10205,
  "peer_id": {
    "_": "PeerChannel",
    "channel_id": 1139260001
  },
  "date": "2026-04-26T14:53:31+00:00",
  "message": "",
  "out": false,
  "mentioned": false,
  "media_unread": false,
  "silent": false,
  "post": true,
  "from_scheduled": false,
  "legacy": false,
  "edit_hide": true,
  "pinned": false,
  "noforwards": false,
  "invert_media": false,
  "offline": false,
  "video_processing_pending": false,
  "paid_suggested_post_stars": false,
  "paid_suggested_post_ton": false,
  "from_id": null,
  "from_boosts_applied": null,
  "from_rank": null,
  "saved_peer_id": null,
  "fwd_from": null,
  "via_bot_id": null,
  "via_business_bot_id": null,
  "reply_to": null,
  "media": {
    "_": "MessageMediaDocument",
    "nopremium": false,
    "spoiler": false,
    "video": false,
    "round": false,
    "voice": false,
    "document": {
      "_": "Document",
      "id": 5931686299219003433,
      "access_hash": 3118564938439874901,
      "file_reference": "b\"\\x02C\\xe7\\xbaa\\x00\\x00'\\xddi\\xf0\\xdb\\n\\x8a\\xf8B._6\\x19\\xbd\\xae\\x9dk\\x05\\xfc\\x81\\xe9\\xc3\"",
      "date": "2021-03-11T08:28:52+00:00",
      "mime_type": "image/webp",
      "size": 11262,
      "dc_id": 4,
      "attributes": [
        {
          "_": "DocumentAttributeImageSize",
          "w": 512,
          "h": 338
        },
        {
          "_": "DocumentAttributeSticker",
          "alt": "💵",
          "stickerset": {
            "_": "InputStickerSetID",
            "id": 96527921098784779,
            "access_hash": -6314345771627571884
          },
          "mask": false,
          "mask_coords": null
        },
        {
          "_": "DocumentAttributeFilename",
          "file_name": "sticker.webp"
        }
      ],
      "thumbs": [
        {
          "_": "PhotoPathSize",
          "type": "j",
          "bytes": "b'\\x1d\\x05\\x97\\t\\xdcRBTYEa\\x88D\\x91\\x82\\x9aB\\x83BGELFB\\x81L\\x87O\\x88M\\x82TH^IL\\x81U\\x90h\\x86ZN\\x80J\\x05\\x91J\\x07\\x88\\x81\\x8c\\x8a\\x8e\\x8a\\x86\\x80\\xa1Y\\xa1\\x87\\x80\\x85H\\x91H\\x93\\x81\\x82\\x8e\\x83\\x90\\x8b\\x82\\x8cP\\xa5H\\xa5\\x95\\x80\\x8c]\\x9b`\\x98D\\x8e\\x92\\x8d\\x9f\\x80\\x87\\x95K\\x97T\\x83KAu\\x8fx\\xa7FC\\x87\\x00\\x8b\\x87\\x07\\x8f\\x88\\x92]\\x9a`\\x9fK\\x86\\xa7\\x95\\x9f\\x87C\\x96a\\x92fABIBKDHHDX\\x86]\\x86C\\x8a\\x81\\x90\\x81\\x86\\x80\\x8cE\\x92\\x81\\x8f\\x8dE\\x97J\\x9f\\x81\\x80\\x82\\x93\\x81\\x95E\\x96U\\xaen\\xacF\\x81MHQHI\\x80N\\x8aZ\\x88GAKJQK\\x80\\x80L\\x87L\\x88C\\x81P\\x82R\\x83C\\x83\\x86\\x86\\x87\\x89\\x82\\x87\\x81\\x90G\\x95H\\x85Q\\x80[\\x83'"
        },
        {
          "_": "PhotoSize",
          "type": "m",
          "w": 320,
          "h": 211,
          "size": 7426
        }
      ],
      "video_thumbs": []
    },
    "alt_documents": [],
    "video_cover": null,
    "video_timestamp": null,
    "ttl_seconds": null
  },
  "reply_markup": null,
  "entities": [],
  "views": 18969,
  "forwards": 0,
  "replies": null,
  "edit_date": "2026-04-26T23:35:36+00:00",
  "post_author": null,
  "grouped_id": null,
  "reactions": {
    "_": "MessageReactions",
    "results": [
      {
        "_": "ReactionCount",
        "reaction": {
          "_": "ReactionEmoji",
          "emoticon": "❤"
        },
        "count": 1,
        "chosen_order": null
      },
      {
        "_": "ReactionCount",
        "reaction": {
          "_": "ReactionEmoji",
          "emoticon": "👍"
        },
        "count": 1,
        "chosen_order": null
      }
    ],
    "min": false,
    "can_see_list": false,
    "reactions_as_tags": false,
    "recent_reactions": [],
    "top_reactors": []
  },
  "restriction_reason": [],
  "ttl_period": null,
  "quick_reply_shortcut_id": null,
  "effect": null,
  "factcheck": null,
  "report_delivery_until_date": null,
  "paid_message_stars": null,
  "suggested_post": null,
  "schedule_repeat_period": null,
  "summary_from_language": null
}