{
  "_": "Message",
  "id": 60887,
  "peer_id": {
    "_": "PeerChannel",
    "channel_id": 1968751894
  },
  "date": "2026-04-19T12:20:26+00:00",
  "message": "@Configir98",
  "out": false,
  "mentioned": false,
  "media_unread": false,
  "silent": false,
  "post": true,
  "from_scheduled": false,
  "legacy": false,
  "edit_hide": false,
  "pinned": false,
  "noforwards": false,
  "invert_media": false,
  "offline": false,
  "video_processing_pending": false,
  "paid_suggested_post_stars": false,
  "paid_suggested_post_ton": false,
  "from_id": null,
  "from_boosts_applied": null,
  "from_rank": null,
  "saved_peer_id": null,
  "fwd_from": null,
  "via_bot_id": null,
  "via_business_bot_id": null,
  "reply_to": null,
  "media": {
    "_": "MessageMediaDocument",
    "nopremium": false,
    "spoiler": false,
    "video": false,
    "round": false,
    "voice": false,
    "document": {
      "_": "Document",
      "id": 5125505493057408594,
      "access_hash": 7914654987185996177,
      "file_reference": "b'\\x02uX\\xc5\\x16\\x00\\x00\\xed\\xd7i\\xf0\\xfc\\x7f\\x11\\xa3\\x0b&\"E\\xdc\\x93l\\xd9\\xc8\\x07\\x16\\x1cS\\xe9'",
      "date": "2026-04-19T12:20:25+00:00",
      "mime_type": "",
      "size": 4912,
      "dc_id": 1,
      "attributes": [
        {
          "_": "DocumentAttributeFilename",
          "file_name": "1216307548.npvt"
        }
      ],
      "thumbs": [],
      "video_thumbs": []
    },
    "alt_documents": [],
    "video_cover": null,
    "video_timestamp": null,
    "ttl_seconds": null
  },
  "reply_markup": {
    "_": "ReplyInlineMarkup",
    "rows": [
      {
        "_": "KeyboardButtonRow",
        "buttons": [
          {
            "_": "KeyboardButtonUrl",
            "text": "رمز مشکل داشت",
            "url": "https://t.me/heyats/1216307548",
            "style": null
          }
        ]
      }
    ]
  },
  "entities": [
    {
      "_": "MessageEntityMention",
      "offset": 0,
      "length": 11
    }
  ],
  "views": 297,
  "forwards": 3,
  "replies": null,
  "edit_date": null,
  "post_author": null,
  "grouped_id": null,
  "reactions": null,
  "restriction_reason": [],
  "ttl_period": null,
  "quick_reply_shortcut_id": null,
  "effect": null,
  "factcheck": null,
  "report_delivery_until_date": null,
  "paid_message_stars": null,
  "suggested_post": null,
  "schedule_repeat_period": null,
  "summary_from_language": null
}