{
  "_": "Message",
  "id": 3294,
  "peer_id": {
    "_": "PeerChannel",
    "channel_id": 3209702364
  },
  "date": "2026-04-23T19:37:27+00:00",
  "message": "http://Supercell.com\n\nوایت لیست شد\nمجدد لعنت بهت فیلترچی نت رو وصل کن🖕\n\n@xszapass 👑",
  "out": false,
  "mentioned": false,
  "media_unread": false,
  "silent": false,
  "post": true,
  "from_scheduled": false,
  "legacy": false,
  "edit_hide": false,
  "pinned": false,
  "noforwards": false,
  "invert_media": false,
  "offline": false,
  "video_processing_pending": false,
  "paid_suggested_post_stars": false,
  "paid_suggested_post_ton": false,
  "from_id": null,
  "from_boosts_applied": null,
  "from_rank": null,
  "saved_peer_id": null,
  "fwd_from": null,
  "via_bot_id": null,
  "via_business_bot_id": null,
  "reply_to": null,
  "media": {
    "_": "MessageMediaWebPage",
    "webpage": {
      "_": "WebPage",
      "id": 1447948942166361230,
      "url": "https://supercell.com/",
      "display_url": "supercell.com",
      "hash": 0,
      "has_large_media": true,
      "video_cover_photo": false,
      "type": "photo",
      "site_name": "Supercell",
      "title": null,
      "description": "Visit Supercell.com and find out more about us and our games.",
      "photo": {
        "_": "Photo",
        "id": 5871749408289306080,
        "access_hash": -954270705374954082,
        "file_reference": "b'\\x00i\\xf0\\xf5L\\xd7\\xad\\xba{\\xc5\\xa5\\x97A\\xaau\\xb6G\\x9e\\x1f\\xee\\x90'",
        "date": "2024-11-09T10:51:16+00:00",
        "sizes": [
          {
            "_": "PhotoStrippedSize",
            "type": "i",
            "bytes": "b'\\x01\\x17(\\x9b\\x1b@>\\xb9\\xa5Y\\xe2\\xe3-\\xb7\\xd7=\\xa9\\x92\\r\\x99b\\x089\\xe3=\\xbe\\x9f\\x9dE\\'\\xfa\\x99\\x1c\\x1c|\\xbc\\xf1\\xc8\\xa3@E\\xb34#?\\xbc\\\\\\nkH\\x87\\x01H9\\xef\\xda\\xb3\\x90.\\x1f.\\x00\\x0c\\x14/\\x1c\\xf3\\xeb\\xfdj\\xe9!\\xca\\x08\\xdb$\\x1f\\x99\\x80\\xeb\\xc5\\x03C\\xb1\\xb8\\x12;QK\\x12\\xedb\\x0f\\'\\xd7\\x1dh\\xa0,Z\\x9a\\xd69\\x98\\x16\\xea\\x062([P\\x8e\\x19\\\\\\xe7\\xbf\\xbd\\x14P\"|qUZ\\xc5\\x1e\\xe1\\xa5gc\\x9e\\xc3\\x81\\x8cb\\x8a(\\x02u\\x85\\x10\\xe5T\\x03\\xebE\\x14P\\x07'"
          },
          {
            "_": "PhotoSize",
            "type": "m",
            "w": 320,
            "h": 180,
            "size": 21139
          },
          {
            "_": "PhotoSize",
            "type": "x",
            "w": 800,
            "h": 450,
            "size": 80503
          },
          {
            "_": "PhotoSize",
            "type": "y",
            "w": 1280,
            "h": 720,
            "size": 166946
          },
          {
            "_": "PhotoSize",
            "type": "w",
            "w": 1920,
            "h": 1080,
            "size": 197065
          }
        ],
        "dc_id": 4,
        "has_stickers": false,
        "video_sizes": []
      },
      "embed_url": null,
      "embed_type": null,
      "embed_width": null,
      "embed_height": null,
      "duration": null,
      "author": null,
      "document": null,
      "cached_page": null,
      "attributes": []
    },
    "force_large_media": true,
    "force_small_media": false,
    "manual": true,
    "safe": false
  },
  "reply_markup": null,
  "entities": [
    {
      "_": "MessageEntityUrl",
      "offset": 0,
      "length": 20
    },
    {
      "_": "MessageEntityCustomEmoji",
      "offset": 69,
      "length": 2,
      "document_id": 5470028837326691625
    },
    {
      "_": "MessageEntityMention",
      "offset": 73,
      "length": 9
    },
    {
      "_": "MessageEntityCustomEmoji",
      "offset": 83,
      "length": 2,
      "document_id": 5053169761232356354
    }
  ],
  "views": 9467,
  "forwards": 31,
  "replies": {
    "_": "MessageReplies",
    "replies": 18,
    "replies_pts": 102860,
    "comments": true,
    "recent_repliers": [
      {
        "_": "PeerUser",
        "user_id": 741047354
      },
      {
        "_": "PeerUser",
        "user_id": 7059673371
      },
      {
        "_": "PeerUser",
        "user_id": 6663950417
      }
    ],
    "channel_id": 2200550029,
    "max_id": 63927,
    "read_max_id": null
  },
  "edit_date": "2026-04-24T12:06:26+00:00",
  "post_author": "امیرپارسا",
  "grouped_id": null,
  "reactions": null,
  "restriction_reason": [],
  "ttl_period": null,
  "quick_reply_shortcut_id": null,
  "effect": null,
  "factcheck": null,
  "report_delivery_until_date": null,
  "paid_message_stars": null,
  "suggested_post": null,
  "schedule_repeat_period": null,
  "summary_from_language": null
}