{
  "_": "Message",
  "id": 3332,
  "peer_id": {
    "_": "PeerChannel",
    "channel_id": 3209702364
  },
  "date": "2026-04-28T14:36:50+00:00",
  "message": "آموزش کامل\nمتود Goose–Relay–VPN\nبصورت PDF\nسرعت: بهتر از MHRV\nحجم: مشابه MHRV\nپیش‌نیاز: نیاز به سرور خارج دارد،\nاما نیازی به MITM و سرتیفیکیت ندارد.\nگیتهاب پروژه:\nhttps://github.com/Kianmhz/GooseRelayVPN",
  "out": false,
  "mentioned": false,
  "media_unread": false,
  "silent": false,
  "post": true,
  "from_scheduled": false,
  "legacy": false,
  "edit_hide": true,
  "pinned": false,
  "noforwards": false,
  "invert_media": false,
  "offline": false,
  "video_processing_pending": false,
  "paid_suggested_post_stars": false,
  "paid_suggested_post_ton": false,
  "from_id": null,
  "from_boosts_applied": null,
  "from_rank": null,
  "saved_peer_id": null,
  "fwd_from": null,
  "via_bot_id": null,
  "via_business_bot_id": null,
  "reply_to": null,
  "media": {
    "_": "MessageMediaDocument",
    "nopremium": false,
    "spoiler": false,
    "video": false,
    "round": false,
    "voice": false,
    "document": {
      "_": "Document",
      "id": 6016880256890182825,
      "access_hash": -2163218769791068853,
      "file_reference": "b'\\x05\\x00\\x00\\x00\\x00\\xbfP+\\xdc\\x00\\x00\\r\\x04i\\xf0\\xf5L\\n\\xfeQ\\xdbBS\\xb0\\xa1\\xa4A\\xb2g\\xb0\\xb8,\\xe3'",
      "date": "2026-04-28T11:21:57+00:00",
      "mime_type": "application/pdf",
      "size": 195733,
      "dc_id": 4,
      "attributes": [
        {
          "_": "DocumentAttributeFilename",
          "file_name": "Goose–Relay–VPN.pdf"
        }
      ],
      "thumbs": [],
      "video_thumbs": []
    },
    "alt_documents": [],
    "video_cover": null,
    "video_timestamp": null,
    "ttl_seconds": null
  },
  "reply_markup": null,
  "entities": [
    {
      "_": "MessageEntityBlockquote",
      "offset": 0,
      "length": 41,
      "collapsed": false
    },
    {
      "_": "MessageEntityBlockquote",
      "offset": 42,
      "length": 106,
      "collapsed": false
    },
    {
      "_": "MessageEntityBlockquote",
      "offset": 148,
      "length": 54,
      "collapsed": false
    },
    {
      "_": "MessageEntityUrl",
      "offset": 162,
      "length": 40
    }
  ],
  "views": 18890,
  "forwards": 901,
  "replies": {
    "_": "MessageReplies",
    "replies": 19,
    "replies_pts": 102860,
    "comments": true,
    "recent_repliers": [
      {
        "_": "PeerUser",
        "user_id": 198041419
      },
      {
        "_": "PeerUser",
        "user_id": 8297559487
      },
      {
        "_": "PeerUser",
        "user_id": 464482603
      }
    ],
    "channel_id": 2200550029,
    "max_id": 65218,
    "read_max_id": null
  },
  "edit_date": "2026-04-28T14:36:53+00:00",
  "post_author": "سال گودمن",
  "grouped_id": 14219096081153852,
  "reactions": null,
  "restriction_reason": [],
  "ttl_period": null,
  "quick_reply_shortcut_id": null,
  "effect": null,
  "factcheck": null,
  "report_delivery_until_date": null,
  "paid_message_stars": null,
  "suggested_post": null,
  "schedule_repeat_period": null,
  "summary_from_language": null
}